3rdparty/dlpack/include/dlpack/dlpack.h
include/mlc/ffi/ffi.hpp
include/mlc/ffi/c_api.h
include/mlc/ffi/core/traits_str.h
include/mlc/ffi/core/object.h
include/mlc/ffi/core/traits_object.h
include/mlc/ffi/core/core.h
include/mlc/ffi/core/utils.h
include/mlc/ffi/core/ref.h
include/mlc/ffi/core/any.h
include/mlc/ffi/core/traits_dtype.h
include/mlc/ffi/core/traits_scalar.h
include/mlc/ffi/core/traits_device.h
include/mlc/ffi/ext/udict.h
include/mlc/ffi/ext/func.h
include/mlc/ffi/ext/func_details.h
include/mlc/ffi/ext/list.h
include/mlc/ffi/ext/dict.h
include/mlc/ffi/ext/str.h
include/mlc/ffi/ext/udict_base.h
include/mlc/ffi/ext/error.h
include/mlc/ffi/ext/ulist.h
include/mlc/ffi/ext/ulist_base.h
mlc/dtype.py
mlc/error.py
mlc/dict.py
mlc/object.py
mlc/__init__.py
mlc/func.py
mlc/list.py
mlc/config.py
mlc/device.py
mlc/testing/__init__.py
mlc/cc/jit.py
mlc/cc/compiler.py
mlc/cc/__init__.py
mlc/cc/loader.py
mlc/lib/libmlc_registry.so
mlc/lib/libmlc_registry_static.a
mlc/_cython/core.pyx
mlc/_cython/exception_utils.py
mlc/_cython/__init__.py
mlc/_cython/core_bridge.py
mlc/_cython/.gitignore
mlc/_cython/core.cpython-313-x86_64-linux-gnu.so
ml_compiler-0.0.3.dist-info/RECORD
ml_compiler-0.0.3.dist-info/entry_points.txt
ml_compiler-0.0.3.dist-info/WHEEL
ml_compiler-0.0.3.dist-info/METADATA
ml_compiler-0.0.3.dist-info/licenses/LICENSE
