Metadata-Version: 2.1
Name: ml-compiler
Version: 0.0.3
Author-Email: PyMLC Authors <junrushao@apache.org>
License:                                  Apache License
Classifier: Programming Language :: Python :: 3
Classifier: Programming Language :: Python :: 3 :: Only
Classifier: License :: OSI Approved :: Apache Software License
Classifier: Intended Audience :: Science/Research
Requires-Python: >=3.9
Requires-Dist: numpy>=1.22
Requires-Dist: ml-dtypes>=0.1
Requires-Dist: setuptools; platform_system == "Windows"
Requires-Dist: pytest; extra == "tests"
Requires-Dist: cython>=3; extra == "dev"
Requires-Dist: pre-commit; extra == "dev"
Requires-Dist: pytest; extra == "dev"
Requires-Dist: pipx; extra == "dev"
Requires-Dist: ipdb; extra == "dev"
Requires-Dist: ruff; extra == "dev"
Requires-Dist: mypy; extra == "dev"
Provides-Extra: tests
Provides-Extra: dev
